LICENSE.txt
MANIFEST.in
README.rst
setup.py
awsps/__init__.py
awsps/awsps.py
awsps.egg-info/PKG-INFO
awsps.egg-info/SOURCES.txt
awsps.egg-info/dependency_links.txt
awsps.egg-info/entry_points.txt
awsps.egg-info/requires.txt
awsps.egg-info/top_level.txt