Metadata-Version: 1.0
Name: awsps
Version: 0.2.0
Summary: AWS Profile Switcher
Home-page: https://github.com/Deepakkothandan/awsps.git
Author: Deepak Kothandan
Author-email: deepak.kdy@gmail.com
License: MIT
Keywords: aws profile switch
Platform: UNKNOWN
